LICENSE.txt
MANIFEST.in
setup.cfg
setup.py
mws/__init__.py
mws/mws.py
mws/utils.py
python_amazon_mws.egg-info/PKG-INFO
python_amazon_mws.egg-info/SOURCES.txt
python_amazon_mws.egg-info/dependency_links.txt
python_amazon_mws.egg-info/not-zip-safe
python_amazon_mws.egg-info/requires.txt
python_amazon_mws.egg-info/top_level.txt