Metadata-Version: 1.1
Name: python-amazon-mws
Version: 0.6
Summary: A python interface for Amazon MWS
Home-page: http://github.com/czpython/python-amazon-mws
Author: Paulo Alvarado
Author-email: commonzenpython@gmail.com
License: LICENSE.txt
Platform: OS Independent
Classifier: Development Status :: 2 - Pre-Alpha
Classifier: Environment :: Web Environment
Classifier: Intended Audience :: Developers
Classifier: License :: OSI Approved :: BSD License
Classifier: Operating System :: OS Independent
Classifier: Programming Language :: Python
Classifier: Topic :: Internet :: WWW/HTTP :: Dynamic Content
Classifier: Topic :: Software Development
Classifier: Topic :: Software Development :: Libraries :: Application Frameworks
Classifier: Programming Language :: Python :: 2
Classifier: Programming Language :: Python :: 2.6
Classifier: Programming Language :: Python :: 2.7
